test/__init__.py
test/benchmark_test.py
test/test_data_parse.py
test/test_filter.py
test/test_if_match.py
test/test_loop_match.py
test/test_match.py
test/test_output.py
test/test_poscar_parse.py
test/test_search.py
test/test_template_match.py
test/test_template_parse.py
test/test_xdacar_parse.py
test/testsymbolnode.py
tsstp/__init__.py
tsstp/datatemplate.py
tsstp/extract_symbol.py
tsstp/filter.py
tsstp/internal_ds.py
tsstp/semantic_model.py
tsstp/template_grammar.lark
tsstp/template_parser.py
tsstp/utils.py
tsstp/input/__init__.py
tsstp/input/file_input.py
tsstp/input/token_grammar.lark
tsstp/matcher/__init__.py
tsstp/matcher/if_matcher.py
tsstp/matcher/loop_matcher.py
tsstp/matcher/multi_template_matcher.py
tsstp/matcher/string_matcher.py
tsstp/matcher/template_matcher.py
tsstp/matcher/template_str_matcher.py
tsstp/output/__init__.py
tsstp/output/result.py
tsstp-0.2.0.dist-info/METADATA
tsstp-0.2.0.dist-info/WHEEL
tsstp-0.2.0.dist-info/entry_points.txt
tsstp-0.2.0.dist-info/top_level.txt
tsstp-0.2.0.dist-info/RECORD
