Metadata-Version: 2.1
Name: tsstp
Version: 0.2.0
Summary: Template semi-structure text parser
Home-page: https://gitlab.com/bmaterials/tsstp
Author: Zhuming Gong; Bing He; 
Author-email: shhebing@qq.com
License: UNKNOWN
Platform: UNKNOWN
Requires-Python: >=3.9
Requires-Dist: lark (==1.1.2)
Requires-Dist: xmltodict (==0.12.0)
